example_pkg/__init__.py
rocknesBetaTest-1.0.0.dist-info/LICENSE.txt
rocknesBetaTest-1.0.0.dist-info/METADATA
rocknesBetaTest-1.0.0.dist-info/WHEEL
rocknesBetaTest-1.0.0.dist-info/top_level.txt
rocknesBetaTest-1.0.0.dist-info/RECORD
