Metadata-Version: 2.1
Name: rocknesBetaTest
Version: 1.0.0
Summary: A small example package
Home-page: https://github.com/rocknes/beta-test
Author: Aritra Sen
Author-email: aritra.iitkgp@gmail.com
License: UNKNOWN
Platform: UNKNOWN
Classifier: Programming Language :: Python :: 3
Classifier: License :: OSI Approved :: MIT License
Classifier: Operating System :: OS Independent
